{"TTXX0001":"Alas",
"TTXX0002":"Atabai",
"TTXX0003":"Atauro",
"TTXX0004":"Atsabe",
"TTXX0005":"Kribasbarique",
"TTXX0006":"Bazartete",
"TTXX0007":"Berau",
"TTXX0008":"Biquele",
"TTXX0009":"Bobonaro",
"TTXX0010":"Ermera",
"TTXX0011":"Fatuberliu",
"TTXX0012":"Hatolina",
"TTXX0013":"Hatoudo",
"TTXX0014":"Laclubar",
"TTXX0015":"Lacluta",
"TTXX0016":"Letefoho",
"TTXX0017":"Lolotoe",
"TTXX0018":"Maliana",
"TTXX0019":"Manatuto",
"TTXX0020":"Maubara",
"TTXX0021":"Maubisse",
"TTXX0022":"Ponta Acoilo",
"TTXX0023":"Ponta Carimbala",
"TTXX0024":"Ponta Gu Ilo",
"TTXX0025":"Ponta Sia Ilo",
"TTXX0026":"Same",
"TTXX0027":"Zumalai",
"TTXX0028":"Adara",
"TTXX0029":"Airport",
"TTXX0030":"Akrema",
"TTXX0031":"Anartutu",
"TTXX0032":"Arlo",
"TTXX0033":"Atekru",
"TTXX0034":"Belem",
"TTXX0035":"Beloi",
"TTXX0036":"Bite",
"TTXX0037":"Doro",
"TTXX0038":"Iliana",
"TTXX0039":"Ilinamu",
"TTXX0040":"Maker",
"TTXX0041":"Masilihu",
"TTXX0042":"Maulako",
"TTXX0043":"Maumeta",
"TTXX0044":"Pala",
"TTXX0045":"Uaroana",
"TTXX0046":"Vatuu",
"TTXX0047":"Vila",
"TTXX0048":"Watupo",
"TTXX0049":"Afumalule",
"TTXX0050":"Aijauana",
"TTXX0051":"Aosnak",
"TTXX0052":"Asabat",
"TTXX0053":"Bambai",
"TTXX0054":"Baoknana",
"TTXX0055":"Baokopael",
"TTXX0056":"Baqui",
"TTXX0057":"Baupat",
"TTXX0058":"Bausiu",
"TTXX0059":"Bebo",
"TTXX0060":"Benais",
"TTXX0061":"Benoko",
"TTXX0062":"Besatoko",
"TTXX0063":"Besemese",
"TTXX0064":"Biele",
"TTXX0065":"Bihala",
"TTXX0066":"Bilahuk",
"TTXX0067":"Bimelo",
"TTXX0068":"Biseo",
"TTXX0069":"Bitana",
"TTXX0070":"Bititim",
"TTXX0071":"Bobonoe",
"TTXX0072":"Bokon",
"TTXX0073":"Bonak",
"TTXX0074":"Bonemese",
"TTXX0075":"Bonemeto",
"TTXX0076":"Bono",
"TTXX0077":"Buinsapi",
"TTXX0078":"Buki",
"TTXX0079":"Buneu",
"TTXX0080":"Bussi",
"TTXX0081":"Citrana",
"TTXX0082":"Cutete",
"TTXX0083":"Ejomenu",
"TTXX0084":"Eonae",
"TTXX0085":"Faiteno",
"TTXX0086":"Fatnuni",
"TTXX0087":"Fatsuba",
"TTXX0088":"Fatuke",
"TTXX0089":"Fatumtasa",
"TTXX0090":"Fatunababo",
"TTXX0091":"Fatuputi",
"TTXX0092":"Fatusene",
"TTXX0093":"Fatututa",
"TTXX0094":"Faut",
"TTXX0095":"Fauteso",
"TTXX0096":"Fautkabe",
"TTXX0097":"Fautmet",
"TTXX0098":"Fuabana",
"TTXX0099":"Fuames",
"TTXX0100":"Fuin",
"TTXX0101":"Fulolo",
"TTXX0102":"Hauana",
"TTXX0103":"Hauknutu",
"TTXX0104":"Huaen",
"TTXX0105":"Hueleo",
"TTXX0106":"Hueneno",
"TTXX0107":"Isu",
"TTXX0108":"Itnan",
"TTXX0109":"Jumati",
"TTXX0110":"Kabana",
"TTXX0111":"Kabukpele",
"TTXX0112":"Kafun",
"TTXX0113":"Kanael",
"TTXX0114":"Kanete",
"TTXX0115":"Kinat",
"TTXX0116":"Kinloki",
"TTXX0117":"Kisan",
"TTXX0118":"Kiubatan",
"TTXX0119":"Kiubiole",
"TTXX0120":"Kiubneko",
"TTXX0121":"Kiubose",
"TTXX0122":"Kiubukif",
"TTXX0123":"Kiukle",
"TTXX0124":"Kiukole",
"TTXX0125":"Kiumina",
"TTXX0126":"Kiupenu",
"TTXX0127":"Kiutunis",
"TTXX0128":"Kobes",
"TTXX0129":"Kolam Cina",
"TTXX0130":"Krusisoh",
"TTXX0131":"Kuafeu",
"TTXX0132":"Kuanakabun",
"TTXX0133":"Kuanana",
"TTXX0134":"Kuanata",
"TTXX0135":"Kuanatui",
"TTXX0136":"Kuangkiu",
"TTXX0137":"Kuangkot",
"TTXX0138":"Kuanisi",
"TTXX0139":"Kuanobe",
"TTXX0140":"Kuantabun",
"TTXX0141":"Kuapal",
"TTXX0142":"Kuatenes",
"TTXX0143":"Kuatnana",
"TTXX0144":"Kuba",
"TTXX0145":"Kuef",
"TTXX0146":"Kuntua",
"TTXX0147":"Kusi",
"TTXX0148":"Lamasi",
"TTXX0150":"Loel",
"TTXX0151":"Maenu",
"TTXX0152":"Mahata",
"TTXX0153":"Mambua",
"TTXX0154":"Manan",
"TTXX0155":"Manunfena",
"TTXX0156":"Manuoef",
"TTXX0157":"Maonnese",
"TTXX0158":"Maquelab",
"TTXX0159":"Masin",
"TTXX0160":"Matanome",
"TTXX0161":"Maunaben",
"TTXX0162":"Menoah",
"TTXX0163":"Meta",
"TTXX0164":"Misi",
"TTXX0165":"Naituna",
"TTXX0166":"Najaimuti",
"TTXX0167":"Najalu",
"TTXX0168":"Naktuka",
"TTXX0169":"Nalaen",
"TTXX0170":"Naofe",
"TTXX0171":"Nefolete",
"TTXX0172":"Nefomtasa",
"TTXX0173":"Nemun",
"TTXX0174":"Nenopen",
"TTXX0175":"Neofmalo",
"TTXX0176":"Neofmetan",
"TTXX0177":"Neofmuti",
"TTXX0178":"Neopnua",
"TTXX0179":"Nepobai",
"TTXX0180":"Netenbitemu",
"TTXX0181":"Netenoke",
"TTXX0182":"Netensuan",
"TTXX0183":"Nianafu",
"TTXX0184":"Nijamtasa",
"TTXX0185":"Nipane",
"TTXX0186":"Nisapenu",
"TTXX0187":"Nitibe",
"TTXX0188":"Noafafo",
"TTXX0189":"Noahluku",
"TTXX0190":"Nobeat",
"TTXX0191":"Noeninan",
"TTXX0192":"Noetoko",
"TTXX0193":"Noke",
"TTXX0194":"Nonkikan",
"TTXX0195":"Nopai",
"TTXX0196":"Nuabatan",
"TTXX0197":"Nuahake",
"TTXX0198":"Nuakbat",
"TTXX0199":"Nuana",
"TTXX0200":"Nubani",
"TTXX0201":"Nuheo",
"TTXX0202":"Numatambing",
"TTXX0203":"Numputu",
"TTXX0204":"Nunafa",
"TTXX0205":"Nunbai",
"TTXX0206":"Nunenau",
"TTXX0207":"Nunete",
"TTXX0208":"Nunfomolo",
"TTXX0209":"Nunkolo",
"TTXX0210":"Nunuhenu",
"TTXX0211":"Nunuhle",
"TTXX0212":"Nuslao",
"TTXX0213":"Oamna",
"TTXX0214":"Oapjumama",
"TTXX0215":"Oe-Cussi",
"TTXX0216":"Oebaha",
"TTXX0217":"Oebaki",
"TTXX0218":"Oebau",
"TTXX0219":"Oebelo",
"TTXX0220":"Oebone",
"TTXX0221":"Oebu",
"TTXX0222":"Oehoso",
"TTXX0223":"Oekum",
"TTXX0224":"Oelajaob",
"TTXX0225":"Oelangkai",
"TTXX0226":"Oelbabai",
"TTXX0227":"Oelelo",
"TTXX0228":"Oelete",
"TTXX0229":"Oelila",
"TTXX0230":"Oelkaem",
"TTXX0231":"Oelnanoe",
"TTXX0232":"Oelole",
"TTXX0233":"Oelpab",
"TTXX0234":"Oemolo",
"TTXX0235":"Oenino",
"TTXX0236":"Oenoa",
"TTXX0237":"Oepauk",
"TTXX0238":"Oepoko",
"TTXX0239":"Oepuah",
"TTXX0240":"Oesena",
"TTXX0241":"Oesilo",
"TTXX0242":"Oesono",
"TTXX0243":"Oetako",
"TTXX0244":"Oetulu",
"TTXX0245":"Pademau",
"TTXX0246":"Padiae",
"TTXX0247":"Palaban",
"TTXX0248":"Palink",
"TTXX0249":"Pante Makasar",
"TTXX0250":"Passabe",
"TTXX0251":"Patikase",
"TTXX0252":"Patmet",
"TTXX0253":"Patoke",
"TTXX0254":"Patputu",
"TTXX0255":"Poasbot",
"TTXX0256":"Postusika",
"TTXX0257":"Pune",
"TTXX0258":"Roti",
"TTXX0259":"Sabela",
"TTXX0260":"Saenpeo",
"TTXX0261":"Sakato",
"TTXX0262":"Sanane",
"TTXX0263":"Santacrus",
"TTXX0264":"Santaroja",
"TTXX0265":"Seklole",
"TTXX0266":"Semoro",
"TTXX0267":"Senaf",
"TTXX0268":"Sipin",
"TTXX0269":"Soin",
"TTXX0270":"Sonafjak",
"TTXX0271":"Sonomnasi",
"TTXX0272":"Sufmuti",
"TTXX0273":"Sumlili",
"TTXX0274":"Tabe",
"TTXX0275":"Taknebo",
"TTXX0276":"Taolen",
"TTXX0277":"Taosero",
"TTXX0278":"Tenae",
"TTXX0279":"Tobo",
"TTXX0280":"Tuames",
"TTXX0281":"Tuinmolo",
"TTXX0282":"Tulaika",
"TTXX0283":"Tulham",
"TTXX0284":"Tumepat",
"TTXX0285":"Tumin",
"TTXX0286":"Ukbatan",
"TTXX0287":"Ulas",
"TTXX0288":"Upsena",
"TTXX0289":"Usafin",
"TTXX0290":"Uthautfoo",
"TTXX0291":"Valverde",
"TTXX0292":"Abafala",
"TTXX0293":"Abat",
"TTXX0294":"Abere",
"TTXX0295":"Abomatebean",
"TTXX0296":"Abuli",
"TTXX0297":"Aburo",
"TTXX0298":"Abuti",
"TTXX0299":"Acaidoroloho",
"TTXX0300":"Acakuata",
"TTXX0301":"Acara",
"TTXX0302":"Acolimamate",
"TTXX0303":"Acubira",
"TTXX0304":"Acubuli",
"TTXX0305":"Acumata",
"TTXX0306":"Adafari",
"TTXX0307":"Adentuik",
"TTXX0308":"Adoi",
"TTXX0309":"Aelaneno",
"TTXX0310":"Aelemilari",
"TTXX0311":"Aelita",
"TTXX0312":"Afa",
"TTXX0313":"Afaca",
"TTXX0314":"Afacaimau",
"TTXX0315":"Afagua Manufai",
"TTXX0316":"Afaia",
"TTXX0317":"Afalari",
"TTXX0318":"Afaloicai",
"TTXX0319":"Afguia",
"TTXX0320":"Afloicai",
"TTXX0321":"Ager",
"TTXX0322":"Agoltama",
"TTXX0323":"Ahegara",
"TTXX0324":"Ahic",
"TTXX0325":"Ahinarai",
"TTXX0326":"Aiabe",
"TTXX0327":"Aiaras",
"TTXX0328":"Aiasa",
"TTXX0329":"Aibana",
"TTXX0330":"Aibitikeou",
"TTXX0331":"Aibote",
"TTXX0332":"Aibutihun",
"TTXX0333":"Aiceo",
"TTXX0334":"Aidabahare",
"TTXX0335":"Aidabaleten",
"TTXX0336":"Aidabamera",
"TTXX0337":"Aidabaraeabe",
"TTXX0338":"Aidabasalala",
"TTXX0339":"Aidac",
"TTXX0340":"Aidaklaran",
"TTXX0341":"Aidaludo",
"TTXX0342":"Aidila",
"TTXX0343":"Aidilalaran",
"TTXX0344":"Aihanexun",
"TTXX0345":"Aihatadiu Leten",
"TTXX0346":"Aihatadiukraic",
"TTXX0347":"Aihatutu",
"TTXX0348":"Aihosan",
"TTXX0349":"Aihou",
"TTXX0350":"Aikau",
"TTXX0351":"Aikurus",
"TTXX0352":"Ailafa",
"TTXX0353":"Ailalec",
"TTXX0354":"Ailau",
"TTXX0355":"Ailebere",
"TTXX0356":"Ailelehu",
"TTXX0357":"Ailelehun",
"TTXX0358":"Aileu",
"TTXX0359":"Aileukota",
"TTXX0360":"Ailili",
"TTXX0361":"Ailisu",
"TTXX0362":"Ailoklaran",
"TTXX0363":"Ailoklaran Selatan",
"TTXX0364":"Ailora",
"TTXX0365":"Ailuli",
"TTXX0366":"Aimalai",
"TTXX0367":"Aimea",
"TTXX0368":"Aimerahun",
"TTXX0369":"Aimerliu",
"TTXX0370":"Aimerulu",
"TTXX0371":"Aimeta",
"TTXX0372":"Aimetahun",
"TTXX0373":"Aimia",
"TTXX0374":"Aimorbada",
"TTXX0375":"Aimutin Laran",
"TTXX0376":"Ainaro",
"TTXX0377":"Ainauain",
"TTXX0378":"Ainesi",
"TTXX0379":"Aioi",
"TTXX0380":"Aiprado",
"TTXX0381":"Airae",
"TTXX0382":"Airai",
"TTXX0383":"Airakalau",
"TTXX0384":"Airamasala",
"TTXX0385":"Airas",
"TTXX0386":"Airiti",
"TTXX0387":"Airliu",
"TTXX0388":"Aisahe",
"TTXX0389":"Aisalgusun",
"TTXX0390":"Aisik",
"TTXX0391":"Aissirimou",
"TTXX0392":"Aisucunuc",
"TTXX0393":"Aitarak",
"TTXX0394":"Aitasiabe",
"TTXX0395":"Aiteas",
"TTXX0396":"Aitehen",
"TTXX0397":"Aitemua",
"TTXX0398":"Aitoi",
"TTXX0399":"Aitos",
"TTXX0400":"Aituha",
"TTXX0401":"Aitularan",
"TTXX0402":"Aitura",
"TTXX0403":"Aituto",
"TTXX0404":"Akadiruhun",
"TTXX0405":"Akadirularan",
"TTXX0406":"Akanunu",
"TTXX0407":"Akarlaran",
"TTXX0408":"Alacafa",
"TTXX0409":"Alala",
"TTXX0411":"Alaua",
"TTXX0412":"Alaua Leten",
"TTXX0413":"Alecou Baru",
"TTXX0414":"Alecou Lama",
"TTXX0415":"Aliambata",
"TTXX0416":"Aliatu",
"TTXX0417":"Alooli",
"TTXX0418":"Alosain",
"TTXX0419":"Amanun",
"TTXX0420":"Amarleza",
"TTXX0421":"Ames",
"TTXX0422":"Anahon",
"TTXX0423":"Anapol",
"TTXX0424":"Anarua",
"TTXX0425":"Anaulu",
"TTXX0426":"Anawaro",
"TTXX0427":"Angkasabaru",
"TTXX0428":"Anicalau",
"TTXX0429":"Anilumu",
"TTXX0430":"Anon",
"TTXX0431":"Apidou",
"TTXX0432":"Arara",
"TTXX0433":"Arcos",
"TTXX0434":"Areain",
"TTXX0435":"Ariana",
"TTXX0436":"Arlaeben",
"TTXX0437":"Arle",
"TTXX0438":"Asio",
"TTXX0439":"Asobea",
"TTXX0440":"Asorlema",
"TTXX0441":"Assafadae",
"TTXX0442":"Assalaino",
"TTXX0443":"Assi",
"TTXX0444":"Assuileten",
"TTXX0445":"Asuikraik",
"TTXX0446":"Asulau",
"TTXX0447":"Asumata",
"TTXX0448":"Asumaten",
"TTXX0449":"Atahoc",
"TTXX0450":"Ataname",
"TTXX0451":"Ataubu",
"TTXX0452":"Atelari",
"TTXX0453":"Ateuaissi",
"TTXX0454":"Atolara",
"TTXX0455":"Atuaben",
"TTXX0456":"Atubrau",
"TTXX0457":"Atubuti",
"TTXX0458":"Atudose",
"TTXX0459":"Atuegas",
"TTXX0460":"Atuela",
"TTXX0461":"Atulara",
"TTXX0462":"Atulaun",
"TTXX0463":"Atumate",
"TTXX0464":"Atupae",
"TTXX0465":"Atupai",
"TTXX0466":"Atus",
"TTXX0467":"Auba",
"TTXX0468":"Aubaca",
"TTXX0469":"Aube",
"TTXX0470":"Audian",
"TTXX0471":"Aumodok",
"TTXX0472":"Ausur",
"TTXX0473":"Ayatan",
"TTXX0474":"Baboro",
"TTXX0475":"Babulo",
"TTXX0476":"Babulu",
"TTXX0477":"Bacaisi",
"TTXX0478":"Bacarui",
"TTXX0479":"Baduro",
"TTXX0480":"Baehana",
"TTXX0481":"Baer",
"TTXX0482":"Baguia",
"TTXX0483":"Bahabunak",
"TTXX0484":"Bahadato",
"TTXX0485":"Bahadic",
"TTXX0486":"Bahafau",
"TTXX0487":"Bahalale",
"TTXX0488":"Bahamori",
"TTXX0489":"Bahaneu",
"TTXX0490":"Bahatata",
"TTXX0491":"Bahulu",
"TTXX0492":"Baiquenilau",
"TTXX0493":"Bairo Alto",
"TTXX0494":"Bairo Ledidere",
"TTXX0495":"Bairo Pite",
"TTXX0496":"Baleo",
"TTXX0497":"Balibar",
"TTXX0498":"Balibo",
"TTXX0499":"Balide",
"TTXX0500":"Balidioan",
"TTXX0501":"Balulin",
"TTXX0502":"Bandeirahun",
"TTXX0503":"Banderahun",
"TTXX0504":"Banedole",
"TTXX0505":"Banegoa",
"TTXX0506":"Banerema",
"TTXX0507":"Banitur",
"TTXX0508":"Baordaikun",
"TTXX0509":"Barialaran",
"TTXX0510":"Barikafa",
"TTXX0511":"Barique",
"TTXX0512":"Barleo",
"TTXX0513":"Barliu",
"TTXX0514":"Barolai",
"TTXX0515":"Barolara",
"TTXX0516":"Baru",
"TTXX0517":"Barubatu",
"TTXX0518":"Batamac",
"TTXX0519":"Batas",
"TTXX0520":"Baticassa",
"TTXX0521":"Batubala",
"TTXX0522":"Batubeleter",
"TTXX0523":"Batueru",
"TTXX0524":"Batugade",
"TTXX0525":"Batumano",
"TTXX0526":"Batumigi",
"TTXX0527":"Batuu",
"TTXX0528":"Batuubu",
"TTXX0529":"Bauana",
"TTXX0530":"Baucau",
"TTXX0531":"Baukama",
"TTXX0532":"Baulela",
"TTXX0533":"Baulesiria",
"TTXX0534":"Baura",
"TTXX0535":"Bauro",
"TTXX0536":"Bausae",
"TTXX0537":"Bauwai",
"TTXX0538":"Bazar",
"TTXX0539":"Beabubu",
"TTXX0540":"Beaco",
"TTXX0541":"Beain",
"TTXX0542":"Beasale",
"TTXX0543":"Bebora",
"TTXX0544":"Beboro",
"TTXX0545":"Bebunuk",
"TTXX0546":"Beco",
"TTXX0547":"Bedik",
"TTXX0548":"Bedois",
"TTXX0549":"Beduku",
"TTXX0550":"Behau",
"TTXX0551":"Beheda",
"TTXX0552":"Beheissi",
"TTXX0553":"Beibutuk",
"TTXX0554":"Beikala",
"TTXX0555":"Beilako A",
"TTXX0556":"Beimau",
"TTXX0557":"Bekaril",
"TTXX0558":"Beko",
"TTXX0559":"Bekosi Atas",
"TTXX0560":"Bekosi Bawah",
"TTXX0561":"Bekumu",
"TTXX0562":"Belako B",
"TTXX0563":"Belas",
"TTXX0564":"Belebato",
"TTXX0565":"Beliwale",
"TTXX0566":"Belola",
"TTXX0567":"Beluat",
"TTXX0568":"Belulik Kraik",
"TTXX0569":"Belulik Leten",
"TTXX0570":"Belumhato",
"TTXX0571":"Bemalai",
"TTXX0572":"Bemanotolu",
"TTXX0573":"Bematua",
"TTXX0574":"Bemetan",
"TTXX0575":"Bemori Babaliurai",
"TTXX0576":"Bemori Sentral",
"TTXX0577":"Bemori Taibesi",
"TTXX0578":"Bemoris",
"TTXX0579":"Benunuk",
"TTXX0580":"Beraka",
"TTXX0581":"Berame",
"TTXX0582":"Berato",
"TTXX0583":"Bercoli",
"TTXX0584":"Bereleu",
"TTXX0585":"Berelisu",
"TTXX0586":"Beremana",
"TTXX0587":"Beremanek",
"TTXX0588":"Beremanu",
"TTXX0589":"Berkate",
"TTXX0590":"Berlorai",
"TTXX0591":"Berluli",
"TTXX0592":"Bertai",
"TTXX0593":"Beru",
"TTXX0594":"Berukulun",
"TTXX0595":"Besakren",
"TTXX0596":"Besidada",
"TTXX0597":"Besite",
"TTXX0598":"Besusu",
"TTXX0599":"Betama",
"TTXX0600":"Betano",
"TTXX0601":"Betecaiana",
"TTXX0602":"Beto Barat",
"TTXX0603":"Beto Timur",
"TTXX0604":"Betonau",
"TTXX0605":"Betorema",
"TTXX0606":"Betoria",
"TTXX0607":"Betulala",
"TTXX0608":"Betulale",
"TTXX0609":"Betulau",
"TTXX0610":"Betupu",
"TTXX0611":"Betutu",
"TTXX0612":"Beuah",
"TTXX0613":"Biaboe",
"TTXX0614":"Biabote",
"TTXX0615":"Biaboti",
"TTXX0616":"Biabusi",
"TTXX0617":"Biacau",
"TTXX0618":"Biadae",
"TTXX0619":"Biadila",
"TTXX0620":"Biae",
"TTXX0621":"Biahian",
"TTXX0622":"Biahoro",
"TTXX0623":"Biamarae",
"TTXX0624":"Biamoas",
"TTXX0625":"Biarua",
"TTXX0626":"Biateo",
"TTXX0627":"Bibaro",
"TTXX0628":"Bibidae",
"TTXX0629":"Bibiluto",
"TTXX0630":"Bibitali",
"TTXX0631":"Bibteron",
"TTXX0632":"Bidau",
"TTXX0633":"Bidik",
"TTXX0634":"Bilekun",
"TTXX0635":"Bilimau",
"TTXX0636":"Biliubu",
"TTXX0637":"Biloko",
"TTXX0638":"Binagua",
"TTXX0639":"Binani",
"TTXX0640":"Binimalo",
"TTXX0641":"Binita",
"TTXX0642":"Bislau",
"TTXX0643":"Bismata",
"TTXX0644":"Bispo Medeiros",
"TTXX0645":"Blaro",
"TTXX0646":"Bleheto",
"TTXX0647":"Blinklala",
"TTXX0648":"Bobe",
"TTXX0649":"Boboe",
"TTXX0650":"Boboleta",
"TTXX0651":"Bobolora",
"TTXX0652":"Bocilai",
"TTXX0653":"Boclaran",
"TTXX0654":"Bodohoo",
"TTXX0655":"Boeana",
"TTXX0656":"Boelema",
"TTXX0657":"Boibau",
"TTXX0658":"Boibun",
"TTXX0659":"Boile",
"TTXX0660":"Bok",
"TTXX0661":"Boleha",
"TTXX0662":"Bolobai",
"TTXX0663":"Bonuk",
"TTXX0664":"Borala",
"TTXX0665":"Boramba",
"TTXX0666":"Borhei",
"TTXX0667":"Borluli",
"TTXX0668":"Boro",
"TTXX0669":"Borofari",
"TTXX0670":"Borogae",
"TTXX0671":"Borohun",
"TTXX0672":"Borolalo",
"TTXX0673":"Borolau",
"TTXX0674":"Boromata",
"TTXX0675":"Boropai",
"TTXX0676":"Boroulo",
"TTXX0677":"Borowali",
"TTXX0678":"Boruc",
"TTXX0679":"Bourawei",
"TTXX0680":"Boutal",
"TTXX0681":"Brahua",
"TTXX0682":"Brogobo",
"TTXX0683":"Bua",
"TTXX0684":"Buadolo",
"TTXX0685":"Buahun",
"TTXX0686":"Bualale",
"TTXX0687":"Buamunir",
"TTXX0688":"Buanomor",
"TTXX0689":"Buanurak",
"TTXX0690":"Buau",
"TTXX0691":"Bubodefo",
"TTXX0692":"Buboha",
"TTXX0693":"Bubolita",
"TTXX0694":"Buboloma",
"TTXX0695":"Bubulau",
"TTXX0696":"Buburia",
"TTXX0697":"Buburlalete",
"TTXX0698":"Buburlaran",
"TTXX0699":"Buburlau",
"TTXX0700":"Buburlolon",
"TTXX0701":"Bubususu",
"TTXX0702":"Bucacoa",
"TTXX0703":"Bucoli",
"TTXX0704":"Bucuk",
"TTXX0705":"Bugas",
"TTXX0706":"Buibau",
"TTXX0707":"Buifu",
"TTXX0708":"Buiguira",
"TTXX0709":"Buihomau",
"TTXX0710":"Buikarin",
"TTXX0711":"Builai",
"TTXX0712":"Builako",
"TTXX0713":"Builicorae",
"TTXX0714":"Builiko",
"TTXX0715":"Buku Mera",
"TTXX0716":"Buloi",
"TTXX0717":"Buloilaun",
"TTXX0718":"Bunabiqui",
"TTXX0719":"Buquila",
"TTXX0720":"Burabahae",
"TTXX0721":"Busakukun",
"TTXX0722":"Buskaulari",
"TTXX0723":"Buteri",
"TTXX0724":"Butileo",
"TTXX0725":"Butinafa",
"TTXX0726":"Butofalo",
"TTXX0727":"Cabirooan",
"TTXX0728":"Cacaven",
"TTXX0729":"Cacaven Lama",
"TTXX0730":"Caibolale",
"TTXX0731":"Caicasa",
"TTXX0732":"Caicassa",
"TTXX0733":"Caicassico",
"TTXX0734":"Caicoletohoho",
"TTXX0735":"Caicoli",
"TTXX0736":"Caicua",
"TTXX0737":"Caidabu",
"TTXX0738":"Caidauai",
"TTXX0739":"Caidenulale",
"TTXX0740":"Caidico",
"TTXX0741":"Caidovalarin",
"TTXX0742":"Caihula",
"TTXX0743":"Cailaco",
"TTXX0744":"Cailara",
"TTXX0745":"Caileli",
"TTXX0746":"Cailetiana",
"TTXX0747":"Cailoibere",
"TTXX0748":"Cailooc",
"TTXX0749":"Cailorodi",
"TTXX0750":"Caimauc Quic",
"TTXX0751":"Caimegi",
"TTXX0752":"Caimegi Ulu",
"TTXX0753":"Cainliu",
"TTXX0754":"Caino",
"TTXX0755":"Caintau",
"TTXX0756":"Caiobilalei",
"TTXX0757":"Cairedo",
"TTXX0758":"Caisido",
"TTXX0759":"Caisoro",
"TTXX0760":"Caissahe",
"TTXX0761":"Caitarahu",
"TTXX0762":"Caitaranau",
"TTXX0763":"Caiua",
"TTXX0764":"Caiuaihoo",
"TTXX0765":"Caiualita",
"TTXX0766":"Camedar",
"TTXX0767":"Canlor",
"TTXX0768":"Carabau",
"TTXX0769":"Caraubalo",
"TTXX0770":"Carbulau",
"TTXX0771":"Caremon",
"TTXX0772":"Carlilo",
"TTXX0773":"Carolema",
"TTXX0774":"Cassa",
"TTXX0775":"Cassait",
"TTXX0776":"Caturlau",
"TTXX0777":"Caudatae",
"TTXX0778":"Caunua",
"TTXX0779":"Caurema",
"TTXX0780":"Ceres",
"TTXX0781":"Chai",
"TTXX0782":"Chailoro",
"TTXX0783":"Chaiuacha Baru",
"TTXX0784":"Chaiuacha Lama",
"TTXX0785":"Charano",
"TTXX0786":"Chauluturo",
"TTXX0787":"Chefamuai",
"TTXX0788":"Chenuloro",
"TTXX0789":"Chomoco",
"TTXX0790":"Choquiro",
"TTXX0791":"Cirata",
"TTXX0792":"Cirilelo",
"TTXX0793":"Clacuc",
"TTXX0794":"Clarecmaruc",
"TTXX0795":"Clidic",
"TTXX0796":"Codo",
"TTXX0797":"Colaco",
"TTXX0798":"Colimau",
"TTXX0799":"Com",
"TTXX0800":"Comaoli",
"TTXX0801":"Comilara",
"TTXX0802":"Condar",
"TTXX0803":"Coroco",
"TTXX0804":"Cotabot",
"TTXX0805":"Cotaissi",
"TTXX0806":"Couguira",
"TTXX0807":"Craricboco",
"TTXX0808":"Cribas",
"TTXX0809":"Cucara",
"TTXX0810":"Cucodere",
"TTXX0811":"Culugia",
"TTXX0812":"Daarobu",
"TTXX0813":"Dacolo",
"TTXX0814":"Dadean Huhun",
"TTXX0815":"Dadubere",
"TTXX0816":"Daemenama",
"TTXX0817":"Daesi",
"TTXX0818":"Dailor",
"TTXX0819":"Dailorluta",
"TTXX0820":"Dair",
"TTXX0821":"Dais",
"TTXX0822":"Daisua",
"TTXX0823":"Dalari",
"TTXX0824":"Dalirisi",
"TTXX0825":"Dalun",
"TTXX0826":"Dambohum",
"TTXX0827":"Darabai",
"TTXX0828":"Daradobi",
"TTXX0829":"Daralata",
"TTXX0830":"Daraloi",
"TTXX0831":"Daramata",
"TTXX0832":"Daraoma",
"TTXX0833":"Darasula",
"TTXX0834":"Dare",
"TTXX0835":"Darhai",
"TTXX0836":"Darinau",
"TTXX0837":"Darlau",
"TTXX0838":"Daro",
"TTXX0839":"Darolema",
"TTXX0840":"Daruasa",
"TTXX0841":"Darudu",
"TTXX0842":"Darulara",
"TTXX0843":"Darulema",
"TTXX0844":"Dassarai",
"TTXX0845":"Datametan",
"TTXX0846":"Datawa",
"TTXX0847":"Datina",
"TTXX0848":"Dato",
"TTXX0849":"Datoleo",
"TTXX0850":"Datolia",
"TTXX0851":"Daudere",
"TTXX0852":"Daulalan",
"TTXX0853":"Daulaturo",
"TTXX0854":"Daule",
"TTXX0855":"Daulelo",
"TTXX0856":"Daurata",
"TTXX0857":"Dauroloc",
"TTXX0858":"Debos",
"TTXX0859":"Debosasumaten",
"TTXX0860":"Defadae",
"TTXX0861":"Defauassi",
"TTXX0862":"Delubo",
"TTXX0863":"Delusuvati",
"TTXX0864":"Dena",
"TTXX0865":"Denehuni",
"TTXX0866":"Denihare",
"TTXX0867":"Deralare",
"TTXX0868":"Derohati",
"TTXX0869":"Deunai",
"TTXX0870":"Diaro",
"TTXX0871":"Dilai",
"TTXX0872":"Dilatorobo",
"TTXX0873":"Dili",
"TTXX0874":"Dilor",
"TTXX0875":"Dilukede",
"TTXX0876":"Dimtete",
"TTXX0877":"Dinbau",
"TTXX0878":"Direma",
"TTXX0879":"Dirgantara",
"TTXX0880":"Dirihatilau",
"TTXX0881":"Diruabe",
"TTXX0882":"Diruana",
"TTXX0883":"Dirularan",
"TTXX0884":"Dirumdesan",
"TTXX0885":"Diwake",
"TTXX0886":"Docoate",
"TTXX0887":"Dorema",
"TTXX0888":"Dosmagar",
"TTXX0889":"Dosmagar Kraik",
"TTXX0890":"Duaderok",
"TTXX0891":"Dualanok",
"TTXX0892":"Ducurai",
"TTXX0893":"Duhoho",
"TTXX0894":"Dulibuti",
"TTXX0895":"Durubasa",
"TTXX0896":"Duyung",
"TTXX0897":"Ecapo",
"TTXX0898":"Eduquele",
"TTXX0899":"Enanice",
"TTXX0900":"Enelaran",
"TTXX0901":"Eratoi",
"TTXX0902":"Eraulo",
"TTXX0903":"Erbean",
"TTXX0904":"Erelolo",
"TTXX0905":"Ergoa",
"TTXX0906":"Ergoi",
"TTXX0907":"Erhetu",
"TTXX0908":"Erito",
"TTXX0909":"Ernaro",
"TTXX0910":"Eroho",
"TTXX0911":"Esloso",
"TTXX0912":"Etevata",
"TTXX0913":"Etipiti",
"TTXX0914":"Facua",
"TTXX0915":"Faculau",
"TTXX0916":"Fahate",
"TTXX0917":"Fahikrin",
"TTXX0918":"Fahilacor",
"TTXX0919":"Fahilain",
"TTXX0920":"Fahilebu",
"TTXX0921":"Fahiluhan",
"TTXX0922":"Fahisoi",
"TTXX0923":"Fahita",
"TTXX0924":"Falimano",
"TTXX0925":"Falohai",
"TTXX0926":"Fanalolo",
"TTXX0927":"Fanice",
"TTXX0928":"Fanulelo",
"TTXX0929":"Fasili",
"TTXX0930":"Fatada",
"TTXX0931":"Fateran",
"TTXX0932":"Fatoalas",
"TTXX0933":"Fatobalon",
"TTXX0934":"Fatobuti",
"TTXX0935":"Fatokkun",
"TTXX0936":"Fatometa",
"TTXX0937":"Fatu Cuac",
"TTXX0938":"Fatu-Maquerec",
"TTXX0939":"Fatuahi",
"TTXX0940":"Fatualas",
"TTXX0941":"Fatubelar",
"TTXX0942":"Fatubese",
"TTXX0943":"Fatubesi",
"TTXX0944":"Fatubessi",
"TTXX0945":"Fatuboec",
"TTXX0946":"Fatubolo",
"TTXX0947":"Fatubossa",
"TTXX0948":"Fatucado",
"TTXX0949":"Fatucahi",
"TTXX0950":"Fatuha",
"TTXX0951":"Fatuhada",
"TTXX0952":"Fatuhosa",
"TTXX0953":"Fatuhou",
"TTXX0954":"Fatukabelak",
"TTXX0955":"Fatukakae",
"TTXX0956":"Fatukao",
"TTXX0957":"Fatukbelak",
"TTXX0958":"Fatukbitiklaran",
"TTXX0959":"Fatukkabuarleten",
"TTXX0960":"Fatuklaran",
"TTXX0961":"Fatukledun",
"TTXX0962":"Fatukmetan",
"TTXX0963":"Fatukoan",
"TTXX0964":"Fatuku",
"TTXX0965":"Fatukuak",
"TTXX0966":"Fatulagung",
"TTXX0967":"Fatulai",
"TTXX0968":"Fatulelo",
"TTXX0969":"Fatulia",
"TTXX0970":"Fatuloda",
"TTXX0971":"Fatuloro",
"TTXX0972":"Fatululit",
"TTXX0973":"Fatumanaro",
"TTXX0974":"Fatumea",
"TTXX0975":"Fatumean",
"TTXX0976":"Fatumering",
"TTXX0977":"Fatumeta",
"TTXX0978":"Fatumotin",
"TTXX0979":"Fatumulih",
"TTXX0980":"Fatunaba",
"TTXX0981":"Fatunapa",
"TTXX0982":"Fatuneso",
"TTXX0983":"Fatunia",
"TTXX0984":"Fatunisin",
"TTXX0985":"Faturaseh",
"TTXX0986":"Faturedelau",
"TTXX0987":"Faturui",
"TTXX0988":"Fatuteke",
"TTXX0989":"Fatuuk",
"TTXX0990":"Fauk",
"TTXX0991":"Faulata",
"TTXX0992":"Fereleometa",
"TTXX0993":"Ferikatuas",
"TTXX0994":"Feriksare",
"TTXX0995":"Festau",
"TTXX0996":"Fisunia",
"TTXX0997":"Fiuren",
"TTXX0998":"Flarsirna",
"TTXX0999":"Flisac",
"TTXX1000":"Foelemea",
"TTXX1001":"Foetete",
"TTXX1002":"Foholulik",
"TTXX1003":"Fohomano",
"TTXX1004":"Fohonaro",
"TTXX1005":"Fohorem",
"TTXX1006":"Fohorua",
"TTXX1007":"Fohua",
"TTXX1008":"Folete",
"TTXX1009":"Fuat",
"TTXX1010":"Fuiloro",
"TTXX1011":"Furaclau",
"TTXX1012":"Futatas",
"TTXX1013":"Futuisin",
"TTXX1014":"Futusin",
"TTXX1015":"Gaelema",
"TTXX1016":"Gaenoa",
"TTXX1017":"Gala",
"TTXX1018":"Galaimata",
"TTXX1019":"Galitas",
"TTXX1020":"Galitaz",
"TTXX1021":"Galusapulu",
"TTXX1022":"Gamana",
"TTXX1023":"Gariana",
"TTXX1024":"Gariuai",
"TTXX1025":"Gaulala",
"TTXX1026":"Genuhaan",
"TTXX1027":"Genutete",
"TTXX1028":"Geroboti",
"TTXX1029":"Gerohata",
"TTXX1030":"Gerotete",
"TTXX1031":"Gerudu",
"TTXX1032":"Gildapil",
"TTXX1033":"Glai",
"TTXX1034":"Gleno",
"TTXX1035":"Gnutur",
"TTXX1036":"Gombei",
"TTXX1037":"Gomhaei",
"TTXX1038":"Gorema",
"TTXX1039":"Goubin",
"TTXX1040":"Goulau",
"TTXX1041":"Goulete",
"TTXX1042":"Goulolo",
"TTXX1043":"Goulora",
"TTXX1044":"Groto",
"TTXX1045":"Grotu",
"TTXX1046":"Gudatas",
"TTXX1047":"Gugolai",
"TTXX1048":"Gugulai",
"TTXX1049":"Gulala",
"TTXX1050":"Gulorlau",
"TTXX1051":"Gulumanu",
"TTXX1052":"Gulumugun",
"TTXX1053":"Gumer",
"TTXX1054":"Gunung Dilarini",
"TTXX1055":"Guriqui",
"TTXX1056":"Guruca",
"TTXX1057":"Haareme",
"TTXX1058":"Habolale",
"TTXX1059":"Haebubo",
"TTXX1060":"Haeconi",
"TTXX1061":"Haeheu",
"TTXX1062":"Haemanu",
"TTXX1063":"Hahihoho",
"TTXX1064":"Hahimau",
"TTXX1065":"Hahitali",
"TTXX1066":"Haitupuca",
"TTXX1067":"Halaena",
"TTXX1068":"Halalmeta",
"TTXX1069":"Haleberliuk",
"TTXX1070":"Halilaran",
"TTXX1071":"Halimea",
"TTXX1072":"Halimea Bawah",
"TTXX1073":"Halimean",
"TTXX1074":"Halimutin",
"TTXX1075":"Halioan",
"TTXX1076":"Haliren",
"TTXX1077":"Hamahun",
"TTXX1078":"Haotio",
"TTXX1079":"Harare",
"TTXX1080":"Harekain",
"TTXX1081":"Harema",
"TTXX1082":"Hareoan",
"TTXX1083":"Harolata",
"TTXX1084":"Hasabut",
"TTXX1085":"Hasain",
"TTXX1086":"Haslaran",
"TTXX1087":"Haslulucmodoc",
"TTXX1088":"Hastetuk",
"TTXX1089":"Hatali",
"TTXX1090":"Hataman",
"TTXX1091":"Hatarlema",
"TTXX1092":"Hataulete",
"TTXX1093":"Hatete",
"TTXX1094":"Hatobato",
"TTXX1095":"Hatobuilico",
"TTXX1096":"Hatobuti",
"TTXX1097":"Hatokade",
"TTXX1098":"Hatolalan",
"TTXX1099":"Hatoleta",
"TTXX1100":"Hatolia",
"TTXX1101":"Hatomalos",
"TTXX1102":"Hatomanuc",
"TTXX1103":"Hatomera",
"TTXX1104":"Hatomotei",
"TTXX1105":"Hatoposi",
"TTXX1106":"Hatoquero",
"TTXX1107":"Hatubou",
"TTXX1108":"Hatuconan",
"TTXX1109":"Hatugau",
"TTXX1110":"Hatugeo",
"TTXX1111":"Hatuhai",
"TTXX1112":"Hatuleta",
"TTXX1113":"Hatulete",
"TTXX1114":"Hatulialete",
"TTXX1115":"Hatululi",
"TTXX1116":"Hatumaleha",
"TTXX1117":"Hatumasi",
"TTXX1118":"Hatumede",
"TTXX1119":"Hatumetaudo",
"TTXX1120":"Hatunau",
"TTXX1121":"Hatupa",
"TTXX1122":"Hatupae",
"TTXX1123":"Hatuqesilete",
"TTXX1124":"Haturae",
"TTXX1125":"Haturema",
"TTXX1126":"Hatusao",
"TTXX1127":"Hatusili",
"TTXX1128":"Hau",
"TTXX1129":"Haubai",
"TTXX1130":"Hauho",
"TTXX1131":"Haukeo",
"TTXX1132":"Haunau",
"TTXX1133":"Haupu",
"TTXX1134":"Haurobu",
"TTXX1135":"Hautato",
"TTXX1136":"Hautbiritalau",
"TTXX1137":"Hautei",
"TTXX1138":"Hautilo",
"TTXX1139":"Heda",
"TTXX1140":"Hedarmea",
"TTXX1141":"Hekar",
"TTXX1142":"Helikei",
"TTXX1143":"Henihuta",
"TTXX1144":"Hera",
"TTXX1145":"Herbau",
"TTXX1146":"Hi",
"TTXX1147":"Hieotmano",
"TTXX1148":"Hisuata",
"TTXX1149":"Hohopu",
"TTXX1150":"Hohorai",
"TTXX1151":"Hohulo",
"TTXX1152":"Hohulu",
"TTXX1153":"Hoinawai",
"TTXX1154":"Holak",
"TTXX1155":"Holarua",
"TTXX1156":"Holba",
"TTXX1157":"Holbelis",
"TTXX1158":"Holbese",
"TTXX1159":"Holgeda",
"TTXX1160":"Holgen",
"TTXX1161":"Holitol",
"TTXX1162":"Holmeser",
"TTXX1163":"Holpilat",
"TTXX1164":"Holsa",
"TTXX1165":"Holtal",
"TTXX1166":"Holuhan",
"TTXX1167":"Home",
"TTXX1168":"Hoololo",
"TTXX1169":"Horooto",
"TTXX1170":"Hotklokat",
"TTXX1171":"Hudilaran",
"TTXX1172":"Huiali",
"TTXX1173":"Huluatin",
"TTXX1174":"Humeta",
"TTXX1175":"Hunahai",
"TTXX1176":"Hunda",
"TTXX1177":"Husbuk",
"TTXX1178":"Hutilarang",
"TTXX1179":"Hutseo",
"TTXX1180":"Ifililig",
"TTXX1181":"Ilalein",
"TTXX1182":"Ilat",
"TTXX1183":"Ilate",
"TTXX1184":"Ilatkora",
"TTXX1185":"Ilatlau",
"TTXX1186":"Ilhago",
"TTXX1187":"Ilicoa",
"TTXX1188":"Ilihuli",
"TTXX1189":"Ililai",
"TTXX1190":"Ililapa",
"TTXX1191":"Ilimano",
"TTXX1192":"Ilimbaba",
"TTXX1193":"Iliomar",
"TTXX1194":"Ilpo",
"TTXX1195":"Ioro",
"TTXX1196":"Iparira",
"TTXX1197":"Iraara",
"TTXX1198":"Irabere",
"TTXX1199":"Irabinhooli",
"TTXX1200":"Irabinleteria",
"TTXX1201":"Iradarate",
"TTXX1202":"Irafala",
"TTXX1203":"Iralafai",
"TTXX1204":"Iraluroto",
"TTXX1205":"Iramer",
"TTXX1206":"Iraono",
"TTXX1207":"Iraosso",
"TTXX1208":"Irara",
"TTXX1209":"Iratchau",
"TTXX1210":"Iratoi",
"TTXX1211":"Irlelo",
"TTXX1212":"Iun",
"TTXX1213":"Jembatankik",
"TTXX1214":"Jimelai",
"TTXX1215":"Kabasfatin",
"TTXX1216":"Kabura",
"TTXX1217":"Kadilale",
"TTXX1218":"Kaibair",
"TTXX1219":"Kaibui",
"TTXX1220":"Kaidaho",
"TTXX1221":"Kaihurulale",
"TTXX1222":"Kaikasa",
"TTXX1223":"Kaikasa Vou",
"TTXX1224":"Kaikasalari",
"TTXX1225":"Kailatulale",
"TTXX1226":"Kailelilema",
"TTXX1227":"Kaileulema",
"TTXX1228":"Kailiti",
"TTXX1229":"Kailoi",
"TTXX1230":"Kailokolaran",
"TTXX1231":"Kailoloho",
"TTXX1232":"Kailulik",
"TTXX1233":"Kaimalehoo",
"TTXX1234":"Kaimegoluli",
"TTXX1235":"Kainunuk",
"TTXX1236":"Kairema",
"TTXX1237":"Kairia",
"TTXX1238":"Kairiri",
"TTXX1239":"Kaisera",
"TTXX1240":"Kaitara",
"TTXX1241":"Kaitarahei",
"TTXX1242":"Kaitcho",
"TTXX1243":"Kaitulai",
"TTXX1244":"Kakai",
"TTXX1245":"Kakamata",
"TTXX1246":"Kakaulidung",
"TTXX1247":"Kalae",
"TTXX1248":"Kalohan",
"TTXX1249":"Kamal Pun",
"TTXX1250":"Kamal Raihei",
"TTXX1251":"Kamalehou",
"TTXX1252":"Kamileten",
"TTXX1253":"Kampung Baru",
"TTXX1254":"Kampungbaru",
"TTXX1255":"Kampungcina",
"TTXX1256":"Kampungpeternakan",
"TTXX1257":"Kanurema",
"TTXX1258":"Kaporo",
"TTXX1259":"Kapuas",
"TTXX1260":"Karabela",
"TTXX1261":"Karanu",
"TTXX1262":"Karaulun",
"TTXX1263":"Karetamute",
"TTXX1264":"Karketu",
"TTXX1265":"Karlele",
"TTXX1266":"Karomate",
"TTXX1267":"Karsabar",
"TTXX1268":"Kartini",
"TTXX1269":"Kartolo",
"TTXX1270":"Kasanafar",
"TTXX1271":"Kasimidei",
"TTXX1272":"Kasmantutu",
"TTXX1273":"Kasmutu",
"TTXX1274":"Katimuben",
"TTXX1275":"Katnaulete",
"TTXX1276":"Katraikraik",
"TTXX1277":"Kaubai",
"TTXX1278":"Kaulala",
"TTXX1279":"Kawauman",
"TTXX1280":"Keduloro",
"TTXX1281":"Kelapa",
"TTXX1282":"Kelisifu",
"TTXX1283":"Kemalehohuru",
"TTXX1284":"Kemalelara",
"TTXX1285":"Kemipu",
"TTXX1286":"Keorudu",
"TTXX1287":"Kepelari",
"TTXX1288":"Kera",
"TTXX1289":"Kerolisa",
"TTXX1290":"Kertapati",
"TTXX1291":"Kiar",
"TTXX1292":"Kibular",
"TTXX1293":"Kicras",
"TTXX1294":"Kilibain",
"TTXX1295":"Kirikoli",
"TTXX1296":"Kirilelo",
"TTXX1297":"Kiru",
"TTXX1298":"Kitutu",
"TTXX1299":"Klaetlau",
"TTXX1300":"Klaso",
"TTXX1301":"Klobor",
"TTXX1302":"Koileki",
"TTXX1303":"Koilima",
"TTXX1304":"Kokoa",
"TTXX1305":"Kolehunu",
"TTXX1306":"Kolimali",
"TTXX1307":"Kolkoli",
"TTXX1308":"Koloana",
"TTXX1309":"Kolobili",
"TTXX1310":"Kolosuma",
"TTXX1311":"Koreo",
"TTXX1312":"Korlule",
"TTXX1313":"Kota",
"TTXX1314":"Kotafoun",
"TTXX1315":"Kotagama",
"TTXX1316":"Kotaheo",
"TTXX1317":"Kotalala",
"TTXX1318":"Kotalara",
"TTXX1319":"Kotalaran",
"TTXX1320":"Kotalaura",
"TTXX1321":"Kotamatan",
"TTXX1322":"Kotamutu",
"TTXX1323":"Kotbauru",
"TTXX1324":"Kotohuinamo",
"TTXX1325":"Kotolau",
"TTXX1326":"Kuitaok",
"TTXX1327":"Kukhata",
"TTXX1328":"Kulau",
"TTXX1329":"Kulidasi",
"TTXX1330":"Kulit",
"TTXX1331":"Kulolo",
"TTXX1332":"Kulolola",
"TTXX1333":"Kuluan",
"TTXX1334":"Kuluhum Atas",
"TTXX1335":"Kuluhum Taibesi Atas",
"TTXX1336":"Kuluhum Tengah",
"TTXX1337":"Kulumba",
"TTXX1338":"Kumahu",
"TTXX1339":"Kumooli",
"TTXX1340":"Kun",
"TTXX1341":"Kunsabibi",
"TTXX1342":"Kusilulik",
"TTXX1343":"Kutole",
"TTXX1344":"Kutulau",
"TTXX1345":"Labubu",
"TTXX1346":"Lacaliu",
"TTXX1347":"Laclo",
"TTXX1348":"Lacluan",
"TTXX1350":"Lacolio",
"TTXX1351":"Lacoloroho",
"TTXX1352":"Lacolu",
"TTXX1353":"Lacouma",
"TTXX1354":"Lacudala",
"TTXX1355":"Ladiki",
"TTXX1356":"Lafandaria",
"TTXX1357":"Lafulau",
"TTXX1358":"Laga",
"TTXX1359":"Lahae",
"TTXX1360":"Lahane",
"TTXX1361":"Laherubi",
"TTXX1362":"Laho",
"TTXX1363":"Lahomea",
"TTXX1364":"Lahululi",
"TTXX1365":"Lahuoae",
"TTXX1366":"Laiara",
"TTXX1367":"Laikara",
"TTXX1368":"Lailaovemati",
"TTXX1369":"Lailima",
"TTXX1370":"Laimata",
"TTXX1371":"Laissorolai",
"TTXX1372":"Laissorolai Craic",
"TTXX1373":"Lakabou",
"TTXX1374":"Lakasori",
"TTXX1375":"Lakatil",
"TTXX1376":"Lakau",
"TTXX1377":"Lakawa",
"TTXX1378":"Lakeko",
"TTXX1379":"Lakenu",
"TTXX1380":"Lakeru Laran",
"TTXX1381":"Laklema",
"TTXX1382":"Laklo",
"TTXX1383":"Laklolema",
"TTXX1384":"Lakluan",
"TTXX1385":"Lakmade",
"TTXX1386":"Lakonakbesik",
"TTXX1387":"Lakonalbabu",
"TTXX1388":"Lakoto",
"TTXX1389":"Laktil",
"TTXX1390":"Laktos",
"TTXX1391":"Lakubu",
"TTXX1392":"Lakulomano",
"TTXX1393":"Lakuuai",
"TTXX1394":"Lale",
"TTXX1395":"Lalebol",
"TTXX1396":"Laleia",
"TTXX1397":"Lalica",
"TTXX1398":"Lalomato",
"TTXX1399":"Lalulai",
"TTXX1400":"Lameklaran",
"TTXX1401":"Lapuru",
"TTXX1402":"Laraluha",
"TTXX1403":"Larameta",
"TTXX1404":"Larifano",
"TTXX1405":"Larigua",
"TTXX1406":"Lariledana",
"TTXX1407":"Larimin",
"TTXX1408":"Larimuta",
"TTXX1409":"Larinacha",
"TTXX1410":"Larisula",
"TTXX1411":"Larmera",
"TTXX1412":"Larubo",
"TTXX1413":"Lasula",
"TTXX1414":"Lasuleten",
"TTXX1415":"Latua",
"TTXX1416":"Lauaba",
"TTXX1417":"Lauabe",
"TTXX1418":"Lauana",
"TTXX1419":"Laucepo Baru",
"TTXX1420":"Laucepo Lama",
"TTXX1421":"Lauclau",
"TTXX1422":"Laucolo",
"TTXX1423":"Lauhare",
"TTXX1424":"Lauhili",
"TTXX1425":"Lauiboronai",
"TTXX1426":"Laulara",
"TTXX1427":"Laulara Lama",
"TTXX1428":"Laulema",
"TTXX1429":"Laumana",
"TTXX1430":"Lauraehou",
"TTXX1431":"Lauro",
"TTXX1432":"Lautekas",
"TTXX1433":"Lautem",
"TTXX1434":"Lauvou",
"TTXX1435":"Lavadae",
"TTXX1436":"Lawado",
"TTXX1437":"Lawakau",
"TTXX1438":"Lebene",
"TTXX1439":"Lebertas",
"TTXX1440":"Lebibo",
"TTXX1441":"Lebihin",
"TTXX1442":"Lebometa",
"TTXX1443":"Leborema",
"TTXX1444":"Lebos",
"TTXX1445":"Lebosalara",
"TTXX1446":"Lebotuto",
"TTXX1447":"Lebuana",
"TTXX1448":"Lebudo",
"TTXX1449":"Lebuhae",
"TTXX1450":"Lebuhai",
"TTXX1451":"Lebuhua",
"TTXX1452":"Lebui",
"TTXX1453":"Lebukuku",
"TTXX1454":"Lebulema",
"TTXX1455":"Lebulugor",
"TTXX1456":"Lebululi",
"TTXX1457":"Lebumeo",
"TTXX1458":"Lebumera",
"TTXX1459":"Lebumerakeo",
"TTXX1460":"Lebumeta",
"TTXX1461":"Leburema",
"TTXX1462":"Lebutilau",
"TTXX1463":"Lebutu",
"TTXX1464":"Lecoala",
"TTXX1465":"Ledatame",
"TTXX1466":"Ledena",
"TTXX1467":"Leguimea",
"TTXX1468":"Lehumera",
"TTXX1469":"Lehutula",
"TTXX1470":"Lei",
"TTXX1471":"Leilor",
"TTXX1472":"Leirema",
"TTXX1473":"Lekese",
"TTXX1474":"Lekilakuana",
"TTXX1475":"Lekitei",
"TTXX1476":"Lela",
"TTXX1477":"Lelalai",
"TTXX1478":"Lelemanu",
"TTXX1479":"Lelobere",
"TTXX1480":"Lemano",
"TTXX1481":"Leo",
"TTXX1482":"Leobore",
"TTXX1483":"Leobudu",
"TTXX1484":"Leobutu",
"TTXX1485":"Leodato",
"TTXX1486":"Leohat",
"TTXX1487":"Leolima",
"TTXX1488":"Leonti",
"TTXX1489":"Leopa",
"TTXX1490":"Leotelo",
"TTXX1491":"Leotelon",
"TTXX1492":"Lepalaka",
"TTXX1493":"Lepguen",
"TTXX1494":"Lepo",
"TTXX1495":"Lepokanua",
"TTXX1496":"Lepos",
"TTXX1497":"Lepulau",
"TTXX1498":"Lequidoe",
"TTXX1499":"Lequiloualo",
"TTXX1500":"Lequliwatu",
"TTXX1501":"Lereado",
"TTXX1502":"Lereira",
"TTXX1503":"Lereloho",
"TTXX1504":"Lese",
"TTXX1505":"Lesibutak",
"TTXX1506":"Lesigatal",
"TTXX1507":"Lesu",
"TTXX1508":"Lesuaben",
"TTXX1509":"Lesubotang",
"TTXX1510":"Lesuboten",
"TTXX1511":"Lesulau",
"TTXX1512":"Lesupu",
"TTXX1513":"Letelaran",
"TTXX1514":"Letemumo",
"TTXX1515":"Leubasa",
"TTXX1516":"Leulara",
"TTXX1517":"Leuque Racabu",
"TTXX1518":"Leuro",
"TTXX1519":"Leuro Lama",
"TTXX1520":"Leva",
"TTXX1521":"Levano",
"TTXX1522":"Liabala",
"TTXX1523":"Liabe",
"TTXX1524":"Liabuta",
"TTXX1525":"Lialaileso",
"TTXX1526":"Lialura",
"TTXX1527":"Liamida",
"TTXX1528":"Lianai",
"TTXX1529":"Lianain",
"TTXX1530":"Liaoli",
"TTXX1531":"Liarafa",
"TTXX1532":"Liaro",
"TTXX1533":"Liawaeoli",
"TTXX1534":"Libagua",
"TTXX1535":"Libaloa",
"TTXX1536":"Libaulelo",
"TTXX1537":"Licore",
"TTXX1538":"Lidulalan",
"TTXX1539":"Lientuto",
"TTXX1540":"Lifau",
"TTXX1541":"Lihina",
"TTXX1542":"Liholau",
"TTXX1543":"Lihutula",
"TTXX1544":"Likisa",
"TTXX1545":"Likisala",
"TTXX1546":"Likitura",
"TTXX1547":"Lilapuho",
"TTXX1548":"Lilitai",
"TTXX1549":"Lilouarica",
"TTXX1550":"Limanaro",
"TTXX1551":"Limiluhi",
"TTXX1552":"Liqirahu",
"TTXX1553":"Liquica",
"TTXX1554":"Liriu",
"TTXX1555":"Lisaico",
"TTXX1556":"Lisalara",
"TTXX1557":"Lisimu",
"TTXX1558":"Lisuabe",
"TTXX1559":"Lisuata",
"TTXX1560":"Liufalo",
"TTXX1561":"Loblala",
"TTXX1562":"Locileu",
"TTXX1563":"Locoda",
"TTXX1564":"Locohu",
"TTXX1565":"Loegolo",
"TTXX1566":"Loharai",
"TTXX1567":"Loidua",
"TTXX1568":"Loihuno",
"TTXX1569":"Loilaku",
"TTXX1570":"Loilari",
"TTXX1571":"Loiquero",
"TTXX1572":"Loirae",
"TTXX1573":"Loiulo",
"TTXX1574":"Lokamalikau",
"TTXX1575":"Lokotui",
"TTXX1576":"Lolesu",
"TTXX1577":"Lolinunu",
"TTXX1578":"Lolo-Toi",
"TTXX1579":"Lolubowogua",
"TTXX1580":"Lomatu",
"TTXX1581":"Loo",
"TTXX1582":"Loohali",
"TTXX1583":"Lookeu",
"TTXX1584":"Lopohoho",
"TTXX1585":"Lopoloho",
"TTXX1586":"Lor",
"TTXX1587":"Lore",
"TTXX1588":"Lori",
"TTXX1589":"Loribia",
"TTXX1590":"Loro",
"TTXX1591":"Lorokida",
"TTXX1592":"Los Palos",
"TTXX1593":"Lospalos",
"TTXX1594":"Lotan",
"TTXX1595":"Loti",
"TTXX1596":"Louiquero",
"TTXX1597":"Loulolo",
"TTXX1598":"Loumate",
"TTXX1599":"Lourba",
"TTXX1600":"Lourbaleten",
"TTXX1601":"Lualari",
"TTXX1602":"Luandau",
"TTXX1603":"Luarai",
"TTXX1604":"Luboria",
"TTXX1605":"Luborice",
"TTXX1606":"Lugabuti",
"TTXX1607":"Lugassa",
"TTXX1608":"Lugu Teho",
"TTXX1609":"Lugululi",
"TTXX1610":"Luhabere",
"TTXX1611":"Luhadora",
"TTXX1612":"Luhanaro",
"TTXX1613":"Luhaoli",
"TTXX1614":"Lukowai",
"TTXX1615":"Lukulaulau",
"TTXX1616":"Lulibau",
"TTXX1617":"Luliheni",
"TTXX1618":"Lululae",
"TTXX1619":"Lumululi",
"TTXX1620":"Lunukhun",
"TTXX1621":"Luquisa",
"TTXX1622":"Lurato",
"TTXX1623":"Lurin",
"TTXX1624":"Lurirema",
"TTXX1625":"Luro",
"TTXX1626":"Luru",
"TTXX1627":"Lurumata",
"TTXX1628":"Lutumutu",
"TTXX1629":"Luturula",
"TTXX1630":"Luwa",
"TTXX1631":"Maabat",
"TTXX1632":"Maahui",
"TTXX1633":"Mabelis",
"TTXX1634":"Mabutease",
"TTXX1635":"Macadai Bawah",
"TTXX1636":"Macadaicima",
"TTXX1637":"Macaducarau",
"TTXX1638":"Macalaco",
"TTXX1639":"Macalira",
"TTXX1640":"Macassar",
"TTXX1641":"Macaussa",
"TTXX1642":"Madaraira",
"TTXX1643":"Madede",
"TTXX1644":"Madehoau",
"TTXX1645":"Maebu",
"TTXX1646":"Magalelor",
"TTXX1647":"Maganutu",
"TTXX1648":"Maibuti",
"TTXX1649":"Maina",
"TTXX1650":"Maior",
"TTXX1651":"Makadai",
"TTXX1652":"Makadiki",
"TTXX1653":"Makalodo",
"TTXX1654":"Makate",
"TTXX1655":"Makdean",
"TTXX1656":"Makokon",
"TTXX1657":"Makous",
"TTXX1658":"Malabe",
"TTXX1659":"Malahara",
"TTXX1660":"Malailada",
"TTXX1661":"Malarahu",
"TTXX1662":"Malarara",
"TTXX1663":"Malebauk",
"TTXX1664":"Malepun",
"TTXX1665":"Malere",
"TTXX1666":"Maleria",
"TTXX1667":"Malete",
"TTXX1668":"Maleteten",
"TTXX1669":"Maliaben",
"TTXX1670":"Malibikan",
"TTXX1671":"Malikeo",
"TTXX1672":"Malilait",
"TTXX1673":"Malileten",
"TTXX1674":"Malilia",
"TTXX1675":"Malilu",
"TTXX1676":"Malimea",
"TTXX1677":"Malioboru",
"TTXX1678":"Maliseran",
"TTXX1679":"Malitada",
"TTXX1680":"Maliubu",
"TTXX1681":"Maloira",
"TTXX1682":"Maloroc",
"TTXX1683":"Malulai",
"TTXX1684":"Maluro",
"TTXX1685":"Malushum",
"TTXX1686":"Mamude",
"TTXX1687":"Mamulak",
"TTXX1688":"Mamurlau",
"TTXX1689":"Manacolohata",
"TTXX1690":"Manama",
"TTXX1691":"Manapaatas",
"TTXX1692":"Manarema",
"TTXX1693":"Manati",
"TTXX1694":"Mancadai Atas",
"TTXX1695":"Maneatun",
"TTXX1696":"Manehat",
"TTXX1697":"Maneikun",
"TTXX1698":"Maneklaran",
"TTXX1699":"Manelima",
"TTXX1700":"Manetkim",
"TTXX1701":"Mangero",
"TTXX1702":"Mangkir",
"TTXX1703":"Mania",
"TTXX1704":"Manico",
"TTXX1705":"Manikin",
"TTXX1706":"Manikun",
"TTXX1707":"Manisu",
"TTXX1708":"Manlala",
"TTXX1709":"Manleoana",
"TTXX1710":"Manleu",
"TTXX1711":"Manluana",
"TTXX1712":"Manohatu",
"TTXX1713":"Manonia",
"TTXX1714":"Manoroni",
"TTXX1715":"Manos",
"TTXX1716":"Manosahe",
"TTXX1717":"Mantarlido",
"TTXX1718":"Mantelau",
"TTXX1719":"Mantilu",
"TTXX1720":"Manuamang",
"TTXX1721":"Manubobo",
"TTXX1722":"Manucati",
"TTXX1723":"Manucatilaten",
"TTXX1724":"Manucibia",
"TTXX1725":"Manufahe",
"TTXX1726":"Manufatia",
"TTXX1727":"Manuhei",
"TTXX1728":"Manukasak",
"TTXX1729":"Manukoliria",
"TTXX1730":"Manulai",
"TTXX1731":"Manulete",
"TTXX1732":"Manuleu",
"TTXX1733":"Manulor",
"TTXX1734":"Manumerah",
"TTXX1735":"Manumeta Rahun",
"TTXX1736":"Manuponihei",
"TTXX1737":"Manuquibia",
"TTXX1738":"Manusae",
"TTXX1739":"Mape",
"TTXX1740":"Mapeop",
"TTXX1741":"Marabia",
"TTXX1742":"Marae",
"TTXX1743":"Maraussa",
"TTXX1744":"Marcoluli",
"TTXX1745":"Marinir",
"TTXX1746":"Marko",
"TTXX1747":"Markoni",
"TTXX1748":"Marobo",
"TTXX1749":"Maroman",
"TTXX1750":"Masau",
"TTXX1751":"Masau Atas",
"TTXX1752":"Masau Bawah",
"TTXX1753":"Mascarenhas",
"TTXX1754":"Mata",
"TTXX1755":"Mata Doro",
"TTXX1756":"Matahoi",
"TTXX1757":"Matai",
"TTXX1758":"Matanova",
"TTXX1759":"Matapati",
"TTXX1760":"Mataruak",
"TTXX1761":"Matilau",
"TTXX1762":"Mauama",
"TTXX1763":"Mauane",
"TTXX1764":"Maubesi",
"TTXX1766":"Maucatar",
"TTXX1767":"Mauchiga",
"TTXX1768":"Maucola",
"TTXX1769":"Maucugun",
"TTXX1770":"Maudekur",
"TTXX1771":"Maudemu",
"TTXX1772":"Maudole",
"TTXX1773":"Maukale",
"TTXX1774":"Maukali",
"TTXX1775":"Maukiki",
"TTXX1776":"Maukurunamo",
"TTXX1777":"Maulahulu",
"TTXX1778":"Maulau",
"TTXX1779":"Maulelo",
"TTXX1780":"Mauloho",
"TTXX1781":"Maulore",
"TTXX1782":"Mauluto",
"TTXX1783":"Maumela",
"TTXX1784":"Maunahei",
"TTXX1785":"Mauneno",
"TTXX1786":"Maununo",
"TTXX1787":"Maurotubuka",
"TTXX1788":"Maurubiassa",
"TTXX1789":"Maurusa",
"TTXX1790":"Mausama",
"TTXX1791":"Mausormata",
"TTXX1792":"Mausoro Mata",
"TTXX1793":"Maussoe",
"TTXX1794":"Mautaloh",
"TTXX1795":"Mautilu",
"TTXX1796":"Mautoba",
"TTXX1797":"Mautobalau",
"TTXX1798":"Mauulo",
"TTXX1799":"Mauuno",
"TTXX1800":"Mazop",
"TTXX1801":"Meallumu",
"TTXX1802":"Megir",
"TTXX1803":"Mehara",
"TTXX1804":"Melabua",
"TTXX1805":"Melelaran",
"TTXX1806":"Melemaga",
"TTXX1807":"Memo",
"TTXX1808":"Meop",
"TTXX1809":"Merdeka",
"TTXX1810":"Merigi",
"TTXX1811":"Metagao",
"TTXX1812":"Metaluli",
"TTXX1813":"Metiaut",
"TTXX1814":"Metinaro",
"TTXX1815":"Metir",
"TTXX1816":"Meuai",
"TTXX1817":"Microde",
"TTXX1818":"Minereng",
"TTXX1819":"Misi",
"TTXX1820":"Mohak",
"TTXX1821":"Moko",
"TTXX1822":"Mokorema",
"TTXX1823":"Moleana",
"TTXX1824":"Mologueng",
"TTXX1825":"Mologuenglana",
"TTXX1826":"Momomento",
"TTXX1827":"Monocati",
"TTXX1828":"Montensaun",
"TTXX1829":"Morae",
"TTXX1830":"Morai",
"TTXX1831":"Moro",
"TTXX1832":"Mota Klaran",
"TTXX1833":"Mota Ulun",
"TTXX1834":"Mota Ulun Timur",
"TTXX1835":"Motaikun",
"TTXX1836":"Motakik",
"TTXX1837":"Motamorak",
"TTXX1838":"Motaulan",
"TTXX1839":"Motaulun Barat",
"TTXX1840":"Motolari",
"TTXX1841":"Motoubu",
"TTXX1842":"Motur",
"TTXX1843":"Mua Pitine",
"TTXX1844":"Muafoso",
"TTXX1845":"Muami",
"TTXX1846":"Muapitine",
"TTXX1847":"Muassufa",
"TTXX1848":"Mubaa",
"TTXX1849":"Mucobubo",
"TTXX1850":"Mude",
"TTXX1851":"Mulia",
"TTXX1852":"Mumana",
"TTXX1853":"Munidailo",
"TTXX1854":"Munobol",
"TTXX1855":"Mutubau",
"TTXX1856":"Muturo",
"TTXX1857":"Naafa",
"TTXX1858":"Nacahun",
"TTXX1859":"Nacaleu",
"TTXX1860":"Nagidal",
"TTXX1861":"Nahaek",
"TTXX1862":"Nahareca",
"TTXX1863":"Naibaroc",
"TTXX1864":"Naidala",
"TTXX1865":"Nainare",
"TTXX1866":"Nairete",
"TTXX1867":"Nalametan",
"TTXX1868":"Namanei",
"TTXX1869":"Namoluti",
"TTXX1870":"Namto",
"TTXX1871":"Nanacuro",
"TTXX1872":"Nandikole",
"TTXX1873":"Nanu",
"TTXX1874":"Narlolo",
"TTXX1875":"Nartutu",
"TTXX1876":"Narunteno",
"TTXX1877":"Nassalue",
"TTXX1878":"Nasuto",
"TTXX1879":"Natare",
"TTXX1880":"Natarici",
"TTXX1881":"Natura",
"TTXX1882":"Naulale",
"TTXX1883":"Nauleau",
"TTXX1884":"Nelayan",
"TTXX1885":"Nelgen",
"TTXX1886":"Nelouai",
"TTXX1887":"Neohoo",
"TTXX1888":"Neoledade",
"TTXX1889":"Nikir",
"TTXX1890":"Noapu",
"TTXX1891":"Nobularan",
"TTXX1892":"Nonomogue",
"TTXX1893":"Nonomoguelao",
"TTXX1894":"Nonuboka",
"TTXX1895":"Noulo",
"TTXX1896":"Nounanaro",
"TTXX1897":"Nova Ancora",
"TTXX1898":"Nuahuc",
"TTXX1899":"Nualata",
"TTXX1900":"Nubadak",
"TTXX1901":"Nularan",
"TTXX1902":"Nunagbae",
"TTXX1903":"Nunira",
"TTXX1904":"Nunoti",
"TTXX1905":"Nunturi",
"TTXX1906":"Nunuana",
"TTXX1907":"Nunubrihate",
"TTXX1908":"Nunudamar",
"TTXX1909":"Nunudoco",
"TTXX1910":"Nunudoi",
"TTXX1911":"Nunufu",
"TTXX1912":"Nunuhou",
"TTXX1913":"Nunulau",
"TTXX1914":"Nunulete",
"TTXX1915":"Nunuli",
"TTXX1916":"Nunulisa",
"TTXX1917":"Nunulu",
"TTXX1918":"Nunumea",
"TTXX1919":"Nunupu",
"TTXX1920":"Nunura",
"TTXX1921":"Nunutali",
"TTXX1922":"Nunutana",
"TTXX1923":"Nunuteten",
"TTXX1924":"Nuren",
"TTXX1925":"Oalgomo",
"TTXX1926":"Obeto",
"TTXX1927":"Oboe",
"TTXX1928":"Obrato",
"TTXX1929":"Obugmil",
"TTXX1930":"Ochochau",
"TTXX1931":"Odelgomo",
"TTXX1932":"Oebaba",
"TTXX1933":"Oebaha",
"TTXX1934":"Oebola",
"TTXX1935":"Oeceli",
"TTXX1936":"Oekiar",
"TTXX1937":"Oelaka",
"TTXX1938":"Oeleo",
"TTXX1939":"Oeleu",
"TTXX1940":"Oemarasi",
"TTXX1941":"Oeminak",
"TTXX1942":"Oepauk",
"TTXX1943":"Oepo",
"TTXX1944":"Oerbora",
"TTXX1945":"Oetapo",
"TTXX1946":"Oeto",
"TTXX1947":"Oeulitai",
"TTXX1948":"Oges",
"TTXX1949":"Ogues",
"TTXX1950":"Ohana",
"TTXX1951":"Ohobin",
"TTXX1952":"Olekata",
"TTXX1953":"Oloolo",
"TTXX1954":"Olopana",
"TTXX1955":"Omelat",
"TTXX1956":"Omucano",
"TTXX1957":"Onebu",
"TTXX1958":"Onerafa",
"TTXX1959":"Onortibalari",
"TTXX1960":"Onosere",
"TTXX1961":"Onuaalas",
"TTXX1962":"Oplegul",
"TTXX1963":"Oralan",
"TTXX1964":"Orana",
"TTXX1965":"Orbeto",
"TTXX1966":"Orema",
"TTXX1967":"Orilo",
"TTXX1968":"Orlalan",
"TTXX1969":"Orlora",
"TTXX1970":"Oroluli",
"TTXX1971":"Oroma",
"TTXX1972":"Orsenaco",
"TTXX1973":"Orun",
"TTXX1974":"Ossoake",
"TTXX1975":"Ossogori",
"TTXX1976":"Ossoguigui",
"TTXX1977":"Ossohuna",
"TTXX1978":"Ossoira",
"TTXX1979":"Ossoluga",
"TTXX1980":"Ossomali",
"TTXX1981":"Ossomeca",
"TTXX1982":"Ossoroa",
"TTXX1983":"Ossowa",
"TTXX1984":"Ossu",
"TTXX1985":"Ossuala",
"TTXX1986":"Ossufaso",
"TTXX1987":"Ostico",
"TTXX1988":"Osuun",
"TTXX1989":"Otcho",
"TTXX1990":"Otete",
"TTXX1991":"Ouelae",
"TTXX1992":"Ozo",
"TTXX1993":"Pabalebu",
"TTXX1994":"Pafuloain",
"TTXX1995":"Pahiluha",
"TTXX1996":"Paihara",
"TTXX1997":"Paio",
"TTXX1998":"Pairara",
"TTXX1999":"Paitalo",
"TTXX2000":"Palaka",
"TTXX2001":"Palapasot",
"TTXX2002":"Palistela",
"TTXX2003":"Palitehu",
"TTXX2004":"Pametapu",
"TTXX2005":"Pandavou",
"TTXX2006":"Pantaikelapa",
"TTXX2007":"Paramin",
"TTXX2008":"Parlamento",
"TTXX2009":"Parol",
"TTXX2010":"Pasarema",
"TTXX2011":"Paschei",
"TTXX2012":"Pasir Putih",
"TTXX2013":"Pasirputih",
"TTXX2014":"Paslete",
"TTXX2015":"Pasmaten",
"TTXX2016":"Patukilat",
"TTXX2017":"Patunero",
"TTXX2018":"Paularan",
"TTXX2019":"Pebago",
"TTXX2020":"Pehefito",
"TTXX2021":"Pelelor",
"TTXX2022":"Perumnas",
"TTXX2023":"Petalara",
"TTXX2024":"Petileti",
"TTXX2025":"Peumate",
"TTXX2026":"Pieguda",
"TTXX2027":"Pipgalak",
"TTXX2028":"Piron",
"TTXX2029":"Pissucaraik",
"TTXX2030":"Pisukaraik",
"TTXX2031":"Pisulara",
"TTXX2032":"Pisulete",
"TTXX2033":"Poalete",
"TTXX2034":"Pocana",
"TTXX2035":"Poehati",
"TTXX2036":"Poelau",
"TTXX2037":"Poelete",
"TTXX2038":"Poepung",
"TTXX2039":"Poerema",
"TTXX2040":"Poetail",
"TTXX2041":"Poetete",
"TTXX2042":"Poguinigue",
"TTXX2043":"Pohei",
"TTXX2044":"Pokolo",
"TTXX2045":"Pomento",
"TTXX2046":"Porehe",
"TTXX2047":"Porema",
"TTXX2048":"Porlamano",
"TTXX2049":"Poros",
"TTXX2050":"Priramatan",
"TTXX2051":"Pualaca",
"TTXX2052":"Puaperchula",
"TTXX2053":"Pugarema",
"TTXX2054":"Pugu",
"TTXX2055":"Pukelete",
"TTXX2056":"Puno",
"TTXX2057":"Puruqua",
"TTXX2058":"Purus",
"TTXX2059":"Qeorema",
"TTXX2060":"Qima",
"TTXX2061":"Queleborouai",
"TTXX2062":"Quelicai",
"TTXX2063":"Quintal Arbiro",
"TTXX2064":"Quintal Bot",
"TTXX2065":"Quintal Qik",
"TTXX2066":"Quintaportugal",
"TTXX2067":"Raano",
"TTXX2068":"Rabei",
"TTXX2069":"Raca",
"TTXX2070":"Racolo",
"TTXX2071":"Radeuman",
"TTXX2072":"Raebou",
"TTXX2073":"Raedolen",
"TTXX2074":"Raelau",
"TTXX2075":"Raeluli",
"TTXX2076":"Raeme",
"TTXX2077":"Raemean",
"TTXX2078":"Raenaba",
"TTXX2079":"Raesoro",
"TTXX2080":"Raetun",
"TTXX2081":"Raha",
"TTXX2082":"Rahameta",
"TTXX2083":"Raibere",
"TTXX2084":"Raibiute",
"TTXX2085":"Raibo",
"TTXX2086":"Raibotilau",
"TTXX2087":"Raibua",
"TTXX2088":"Raibuti",
"TTXX2089":"Raicala",
"TTXX2090":"Raidu",
"TTXX2091":"Raifila",
"TTXX2092":"Raifusa",
"TTXX2093":"Raifusu",
"TTXX2094":"Raiglelu",
"TTXX2095":"Raiguesa",
"TTXX2096":"Raihun",
"TTXX2097":"Raila",
"TTXX2098":"Railaco",
"TTXX2099":"Railakopu",
"TTXX2100":"Railete",
"TTXX2101":"Railisu",
"TTXX2102":"Railuli",
"TTXX2103":"Railurin",
"TTXX2104":"Raimaso",
"TTXX2105":"Raimaten",
"TTXX2106":"Raimea",
"TTXX2107":"Raimeda",
"TTXX2108":"Raimera",
"TTXX2109":"Raimerahai",
"TTXX2110":"Raimerahei",
"TTXX2111":"Raimerak",
"TTXX2112":"Raimerhai",
"TTXX2113":"Raimia",
"TTXX2114":"Raipusa",
"TTXX2115":"Rairema",
"TTXX2116":"Rairobo",
"TTXX2117":"Raisoro",
"TTXX2118":"Raitahu",
"TTXX2119":"Raiubu",
"TTXX2120":"Raiulun",
"TTXX2121":"Rajawali",
"TTXX2122":"Ralan",
"TTXX2123":"Ramaskora",
"TTXX2124":"Ramiah",
"TTXX2125":"Ranac",
"TTXX2126":"Ranok",
"TTXX2127":"Rauhassa",
"TTXX2128":"Raumaco",
"TTXX2129":"Reabuticeon",
"TTXX2130":"Realia",
"TTXX2131":"Reamori",
"TTXX2132":"Redilaran",
"TTXX2133":"Regoa",
"TTXX2134":"Rehato",
"TTXX2135":"Rehatu",
"TTXX2136":"Rehatun",
"TTXX2137":"Reiglelu",
"TTXX2138":"Reissoro",
"TTXX2139":"Rekoalepa",
"TTXX2140":"Relolisa",
"TTXX2141":"Rematu",
"TTXX2142":"Rembor",
"TTXX2143":"Remexio",
"TTXX2144":"Remian",
"TTXX2145":"Renatu",
"TTXX2146":"Reododok",
"TTXX2147":"Riadae",
"TTXX2148":"Riaheu",
"TTXX2149":"Rialaun",
"TTXX2150":"Riamori",
"TTXX2151":"Riatoni",
"TTXX2152":"Riatu",
"TTXX2153":"Rigoa",
"TTXX2154":"Rihiu",
"TTXX2155":"Rilau",
"TTXX2156":"Rileko",
"TTXX2157":"Rimori",
"TTXX2158":"Risso",
"TTXX2159":"Rita",
"TTXX2160":"Ritabou",
"TTXX2161":"Ritiogoro",
"TTXX2162":"Ritiudu",
"TTXX2163":"Ritutu",
"TTXX2164":"Robai",
"TTXX2165":"Rofo",
"TTXX2166":"Rokon",
"TTXX2167":"Roruli",
"TTXX2168":"Roto",
"TTXX2169":"Rotutu",
"TTXX2170":"Roulu",
"TTXX2171":"Rumbia",
"TTXX2172":"Rumotau",
"TTXX2173":"Russu",
"TTXX2174":"Russulau",
"TTXX2175":"Rusulau",
"TTXX2176":"Ruta",
"TTXX2177":"Sabaama",
"TTXX2178":"Sabagulau",
"TTXX2179":"Sabandar",
"TTXX2180":"Sabarakalara",
"TTXX2181":"Sabelu",
"TTXX2182":"Sabereke",
"TTXX2183":"Sabomata",
"TTXX2184":"Saboria",
"TTXX2185":"Sabulau",
"TTXX2186":"Sabuli",
"TTXX2187":"Saburai",
"TTXX2188":"Saburapo",
"TTXX2189":"Sacoco",
"TTXX2190":"Sadahor",
"TTXX2191":"Saebau",
"TTXX2192":"Saebere",
"TTXX2193":"Saelari",
"TTXX2194":"Saharaitaurema",
"TTXX2195":"Saheu",
"TTXX2196":"Sakoko",
"TTXX2197":"Salai",
"TTXX2198":"Salara",
"TTXX2199":"Salasa",
"TTXX2200":"Salele",
"TTXX2201":"Samadae",
"TTXX2202":"Samadare",
"TTXX2203":"Samafano",
"TTXX2204":"Samagata",
"TTXX2205":"Samaguia",
"TTXX2206":"Samaira",
"TTXX2207":"Samalai",
"TTXX2208":"Samalakuliba",
"TTXX2209":"Samalalu",
"TTXX2210":"Samalari",
"TTXX2211":"Samaleo",
"TTXX2212":"Samalete",
"TTXX2213":"Samaliurai",
"TTXX2214":"Samalogo",
"TTXX2215":"Samanaro",
"TTXX2216":"Samara",
"TTXX2217":"Samatrai",
"TTXX2219":"Samelau",
"TTXX2220":"Samutaben",
"TTXX2221":"Sanfuk",
"TTXX2222":"Santacruz",
"TTXX2223":"Santana",
"TTXX2224":"Santontonio",
"TTXX2225":"Sapso",
"TTXX2226":"Sardoli",
"TTXX2227":"Sare",
"TTXX2228":"Sarelari",
"TTXX2229":"Sarin",
"TTXX2230":"Sarlala",
"TTXX2231":"Sasahi",
"TTXX2232":"Sassa",
"TTXX2233":"Sau",
"TTXX2234":"Sauacassa",
"TTXX2235":"Sauria",
"TTXX2236":"Savarica",
"TTXX2237":"Sawarika",
"TTXX2238":"Scarema",
"TTXX2239":"Sckar",
"TTXX2240":"Searema",
"TTXX2241":"Seisal",
"TTXX2242":"Seisal Baru",
"TTXX2243":"Selegoa",
"TTXX2244":"Selihasan",
"TTXX2245":"Selucin",
"TTXX2246":"Semautleten",
"TTXX2247":"Sentral",
"TTXX2248":"Sepelata",
"TTXX2249":"Serankotek",
"TTXX2250":"Serelau",
"TTXX2251":"Serema",
"TTXX2252":"Serenica",
"TTXX2253":"Sesurai",
"TTXX2254":"Setiara",
"TTXX2255":"Sialimo",
"TTXX2256":"Siamado",
"TTXX2257":"Sibarceon",
"TTXX2258":"Sibuni",
"TTXX2259":"Sidodadi",
"TTXX2260":"Sidole",
"TTXX2261":"Siguilaba",
"TTXX2262":"Silagolo",
"TTXX2263":"Siliboro",
"TTXX2264":"Silvicola",
"TTXX2265":"Simarema",
"TTXX2266":"Simohei",
"TTXX2267":"Simugol",
"TTXX2268":"Siquilari",
"TTXX2269":"Siralari",
"TTXX2270":"Sirebuu",
"TTXX2271":"Sirimana",
"TTXX2272":"Sirui",
"TTXX2273":"Sisicolema",
"TTXX2274":"Soatala",
"TTXX2275":"Soba",
"TTXX2276":"Socemera",
"TTXX2277":"Sofa",
"TTXX2278":"Sogau",
"TTXX2279":"Soibada",
"TTXX2280":"Soikili",
"TTXX2281":"Solehae",
"TTXX2282":"Soloi",
"TTXX2283":"Soloresi",
"TTXX2284":"Solugolo",
"TTXX2285":"Somoco",
"TTXX2286":"Sono",
"TTXX2287":"Soraha",
"TTXX2288":"Soro",
"TTXX2289":"Soro Kecil",
"TTXX2290":"Sorocama",
"TTXX2291":"Sorogua",
"TTXX2292":"Sorolai",
"TTXX2293":"Sorolua",
"TTXX2294":"Soronaureci",
"TTXX2295":"Sosoana",
"TTXX2296":"Sosoher",
"TTXX2297":"Sou",
"TTXX2298":"Souro",
"TTXX2299":"Squeli",
"TTXX2300":"Suai",
"TTXX2301":"Suataici",
"TTXX2302":"Subalesu",
"TTXX2303":"Subau",
"TTXX2304":"Sucairau",
"TTXX2305":"Sucatin",
"TTXX2306":"Suileo",
"TTXX2307":"Sukabelulik",
"TTXX2308":"Sukabilaran",
"TTXX2309":"Sukaerlaran",
"TTXX2310":"Sukaren",
"TTXX2311":"Sukuloro",
"TTXX2312":"Sulilako",
"TTXX2313":"Suliwa",
"TTXX2314":"Suriubu",
"TTXX2315":"Surocraic",
"TTXX2316":"Surpatin",
"TTXX2317":"Suruhati",
"TTXX2318":"Surukraik",
"TTXX2319":"Susan",
"TTXX2320":"Susurema",
"TTXX2321":"Suwerkeke",
"TTXX2322":"Tabere",
"TTXX2323":"Tahagamo",
"TTXX2324":"Taibesi",
"TTXX2325":"Taimea",
"TTXX2326":"Taiubu",
"TTXX2327":"Takasana",
"TTXX2328":"Talaubu",
"TTXX2329":"Talebo",
"TTXX2330":"Taleta",
"TTXX2331":"Talifelo",
"TTXX2332":"Talilaran",
"TTXX2333":"Talimoro",
"TTXX2334":"Talioan",
"TTXX2335":"Talite",
"TTXX2336":"Talitu",
"TTXX2337":"Talitu Lama",
"TTXX2338":"Talo",
"TTXX2339":"Tamaro",
"TTXX2340":"Tamaro Lama",
"TTXX2341":"Tamitaro",
"TTXX2342":"Tanalale",
"TTXX2343":"Tancae",
"TTXX2344":"Tanusa",
"TTXX2345":"Tapo",
"TTXX2346":"Tapoabe",
"TTXX2347":"Tapoboten",
"TTXX2348":"Tapoinea",
"TTXX2349":"Tarabula",
"TTXX2350":"Taradae",
"TTXX2351":"Taradiga",
"TTXX2352":"Tarmausoru",
"TTXX2353":"Taroman",
"TTXX2354":"Tashilin",
"TTXX2355":"Tasmil",
"TTXX2356":"Tasqolo",
"TTXX2357":"Tatabaoria",
"TTXX2358":"Tatadere",
"TTXX2359":"Tataeulu",
"TTXX2360":"Tatalalarin",
"TTXX2361":"Tatilsame",
"TTXX2362":"Tatiri Baru",
"TTXX2363":"Tatiri Lama",
"TTXX2364":"Tatodere",
"TTXX2365":"Taubere",
"TTXX2366":"Taumrian",
"TTXX2367":"Tautalo",
"TTXX2368":"Tawalolo",
"TTXX2369":"Tebabui",
"TTXX2370":"Teda",
"TTXX2371":"Tegal",
"TTXX2372":"Tehtuko",
"TTXX2373":"Tekinomata",
"TTXX2374":"Telibudae",
"TTXX2375":"Teolale",
"TTXX2376":"Tepa",
"TTXX2377":"Teras",
"TTXX2378":"Terlora",
"TTXX2379":"Terobala",
"TTXX2380":"Tesigele",
"TTXX2381":"Tetilawai",
"TTXX2382":"Tetomori",
"TTXX2383":"Tetumori",
"TTXX2384":"Teuro",
"TTXX2385":"Tiarlelo",
"TTXX2386":"Tibar",
"TTXX2387":"Tidibesse",
"TTXX2388":"Tidir",
"TTXX2389":"Tilomar",
"TTXX2390":"Tirifalo",
"TTXX2391":"Tirilolo",
"TTXX2392":"Tirimos",
"TTXX2393":"Titibauria",
"TTXX2394":"Titibuti",
"TTXX2395":"Titilari",
"TTXX2396":"Titiravem",
"TTXX2397":"Tititir",
"TTXX2398":"Tlibugeo",
"TTXX2399":"Tobau",
"TTXX2400":"Tobolo",
"TTXX2401":"Tobur",
"TTXX2402":"Tohumeta",
"TTXX2403":"Toileru",
"TTXX2404":"Toileso",
"TTXX2405":"Tolema",
"TTXX2406":"Tomanamo",
"TTXX2407":"Tonero",
"TTXX2408":"Tonobibi",
"TTXX2409":"Torilalan",
"TTXX2410":"Tradukoma",
"TTXX2411":"Trisula",
"TTXX2412":"Tua Koin Eco-Village",
"TTXX2413":"Tuanalaran",
"TTXX2414":"Tudoula",
"TTXX2415":"Tuha",
"TTXX2416":"Tuhilu Craic",
"TTXX2417":"Tuhilu Leten",
"TTXX2418":"Tukarocoiloco",
"TTXX2419":"Tukeu",
"TTXX2420":"Tulaiduk",
"TTXX2421":"Tulaiduk Bawah",
"TTXX2422":"Tulaoli",
"TTXX2423":"Tunlero",
"TTXX2424":"Tunomanu",
"TTXX2425":"Tunupahi",
"TTXX2426":"Tuquetin",
"TTXX2427":"Turema",
"TTXX2428":"Turiscai",
"TTXX2429":"Turiscailau",
"TTXX2430":"Turlio",
"TTXX2431":"Turon",
"TTXX2432":"Tutu Luro",
"TTXX2433":"Tutuala",
"TTXX2434":"Tutubaba",
"TTXX2435":"Tutufili",
"TTXX2436":"Tuturema",
"TTXX2437":"Uabuu",
"TTXX2438":"Uacilava",
"TTXX2439":"Uadaboro",
"TTXX2440":"Uagabuta",
"TTXX2441":"Uaho",
"TTXX2442":"Uaiae",
"TTXX2443":"Uaibeana",
"TTXX2444":"Uaibobo",
"TTXX2445":"Uaiboila",
"TTXX2446":"Uaibu",
"TTXX2447":"Uaicai",
"TTXX2448":"Uaicainaro",
"TTXX2449":"Uaicana",
"TTXX2450":"Uaicuha",
"TTXX2451":"Uaidaba",
"TTXX2452":"Uaidora",
"TTXX2453":"Uaigae",
"TTXX2454":"Uaiharchoo",
"TTXX2455":"Uaiheda",
"TTXX2456":"Uailabere",
"TTXX2457":"Uailacama",
"TTXX2458":"Uailaha",
"TTXX2459":"Uailao",
"TTXX2460":"Uaimanuboe",
"TTXX2461":"Uaimare",
"TTXX2462":"Uaimata",
"TTXX2463":"Uaimoribere",
"TTXX2464":"Uaineque",
"TTXX2465":"Uairiu",
"TTXX2466":"Uaisa",
"TTXX2467":"Uaisarigo",
"TTXX2468":"Uaisimo",
"TTXX2469":"Uaitahu",
"TTXX2470":"Uaitalibu",
"TTXX2471":"Uaitalitua",
"TTXX2472":"Uaitame",
"TTXX2473":"Uaitoco",
"TTXX2474":"Uaitoki",
"TTXX2475":"Uaitunau",
"TTXX2476":"Uaitutumata",
"TTXX2477":"Ualeten",
"TTXX2478":"Ualiu",
"TTXX2479":"Uanamibere",
"TTXX2480":"Uanisi",
"TTXX2481":"Uaniuma",
"TTXX2482":"Uaraba",
"TTXX2483":"Uarau",
"TTXX2484":"Uarinana",
"TTXX2485":"Uaroro",
"TTXX2486":"Uassabolo",
"TTXX2487":"Uasufa",
"TTXX2488":"Uat",
"TTXX2489":"Uatabo",
"TTXX2490":"Uatalano",
"TTXX2491":"Uatalio",
"TTXX2492":"Uatalolo",
"TTXX2493":"Uatamatar",
"TTXX2494":"Uatatefo",
"TTXX2495":"Uato-Carbau",
"TTXX2496":"Uatobita",
"TTXX2497":"Uatobono",
"TTXX2498":"Uatocarabau",
"TTXX2499":"Uatodere",
"TTXX2500":"Uatolari",
"TTXX2501":"Uatolia",
"TTXX2502":"Uatora",
"TTXX2503":"Uatosaholi",
"TTXX2504":"Uatoua",
"TTXX2505":"Uatoue",
"TTXX2506":"Uatu Manutuku",
"TTXX2507":"Uatuasa",
"TTXX2508":"Uatubala",
"TTXX2509":"Uatubelaoli",
"TTXX2510":"Uatulari",
"TTXX2511":"Uatulesu",
"TTXX2512":"Uatumissa",
"TTXX2513":"Uaturau",
"TTXX2514":"Uaule",
"TTXX2515":"Ucamuni",
"TTXX2516":"Ucobai",
"TTXX2517":"Uculoli",
"TTXX2518":"Uduai",
"TTXX2519":"Ueabae",
"TTXX2520":"Uebicas",
"TTXX2521":"Uecobuti",
"TTXX2522":"Uehuafa",
"TTXX2523":"Uelaku",
"TTXX2524":"Ulabute",
"TTXX2525":"Ulacn",
"TTXX2526":"Ulolaco",
"TTXX2527":"Ulturo",
"TTXX2528":"Uluana",
"TTXX2529":"Uluisi",
"TTXX2530":"Umaanaico",
"TTXX2531":"Umaberloic",
"TTXX2532":"Umaboco",
"TTXX2533":"Umabooh",
"TTXX2534":"Umabot",
"TTXX2535":"Umacuarec",
"TTXX2536":"Umaheuk",
"TTXX2537":"Umahurai",
"TTXX2538":"Umaiuk",
"TTXX2539":"Umakerek",
"TTXX2540":"Umaklaran",
"TTXX2541":"Umaliurai",
"TTXX2542":"Umalor",
"TTXX2543":"Umamean",
"TTXX2544":"Umanaruk",
"TTXX2545":"Umannaico",
"TTXX2546":"Umaquic",
"TTXX2547":"Umarama",
"TTXX2548":"Umasau",
"TTXX2549":"Umasurat",
"TTXX2550":"Umatolu",
"TTXX2551":"Umatunau",
"TTXX2552":"Unafo",
"TTXX2553":"Unil",
"TTXX2554":"Urado",
"TTXX2555":"Urahou",
"TTXX2556":"Urema",
"TTXX2557":"Urhou",
"TTXX2558":"Urletefoho",
"TTXX2559":"Urletepoho",
"TTXX2560":"Urluli",
"TTXX2561":"Uro",
"TTXX2562":"Urtali",
"TTXX2563":"Urupadan",
"TTXX2564":"Utimori",
"TTXX2565":"Vailana",
"TTXX2566":"Vailoro",
"TTXX2567":"Vailovaia",
"TTXX2568":"Vasotoi",
"TTXX2569":"Vatalara",
"TTXX2570":"Vataomar",
"TTXX2571":"Vatuguili",
"TTXX2572":"Vatuleurai",
"TTXX2573":"Vatumori",
"TTXX2574":"Vatunau",
"TTXX2575":"Vatuvei",
"TTXX2576":"Vaurotubuka",
"TTXX2577":"Vavikinia",
"TTXX2578":"Vawinana",
"TTXX2579":"Vazetida Algar",
"TTXX2580":"Vemasse",
"TTXX2581":"Venilale",
"TTXX2582":"Vero",
"TTXX2583":"Vessa",
"TTXX2584":"Vessoro",
"TTXX2585":"Vessuro",
"TTXX2586":"Vila Verde",
"TTXX2587":"Vilanova",
"TTXX2588":"Viqueque",
"TTXX2589":"Virdolosa",
"TTXX2590":"Visto",
"TTXX2591":"Vitanau",
"TTXX2592":"Waabe",
"TTXX2593":"Wabere",
"TTXX2594":"Waicadi",
"TTXX2595":"Waidau",
"TTXX2596":"Waiderek",
"TTXX2597":"Waidua",
"TTXX2598":"Wainuno",
"TTXX2599":"Wairoke",
"TTXX2600":"Walabaru",
"TTXX2601":"Walalama",
"TTXX2602":"Walawau",
"TTXX2603":"Waniria",
"TTXX2604":"Waniuma",
"TTXX2605":"Wategas",
"TTXX2606":"Watuadalara",
"TTXX2607":"Watubau",
"TTXX2608":"Waturau",
"TTXX2609":"Waudu",
"TTXX2610":"Waupu",
"TTXX2611":"Webani",
"TTXX2612":"Wecian",
"TTXX2613":"Wedauberek",
"TTXX2614":"Wefau",
"TTXX2615":"Weklese",
"TTXX2616":"Welaluhu",
"TTXX2617":"Weluli",
"TTXX2618":"Wemaubodak",
"TTXX2619":"Wemer",
"TTXX2620":"Werulun",
"TTXX2621":"Wesi",
"TTXX2622":"Wiwik",
"TTXX2623":"Xanana Gusm",
"TTXX2624":"Zefaliu",
"TTXX2625":"Zobelis",
"TTXX2626":"Zobete",
"TTXX2627":"Zoilpo",
"TTXX2628":"Zulo",
"TTXX2629":"Zulokota",
"TTXX2630":"Zulotos"}